github/__init__.py
github/__main__.py
github/argparser.py
github/authentication.py
github/cli_handler.py
github/cli_printer.py
github/github_controller.py
github/logger.py
github/common/InvalidAPIKeyException.py
github/common/InvalidNumberOfArgumentsException.py
github/common/__init__.py
github/common/deprecated_decorator.py
github/common/graphql_utils.py
github/common/rest_utils.py
github/queries/graphQL_mutation.py
github/queries/graphQL_query.py
github_cli_app-1.0.1.dist-info/DESCRIPTION.rst
github_cli_app-1.0.1.dist-info/METADATA
github_cli_app-1.0.1.dist-info/RECORD
github_cli_app-1.0.1.dist-info/WHEEL
github_cli_app-1.0.1.dist-info/entry_points.txt
github_cli_app-1.0.1.dist-info/metadata.json
github_cli_app-1.0.1.dist-info/top_level.txt
